django_qiyu_utils/__init__.py
django_qiyu_utils/div_node/__init__.py
django_qiyu_utils/div_node/div_node.py
django_qiyu_utils/env.py
django_qiyu_utils/redirect.py
django_qiyu_utils/settings.py
django_qiyu_utils-0.5.0.dist-info/LICENSE
django_qiyu_utils-0.5.0.dist-info/METADATA
django_qiyu_utils-0.5.0.dist-info/WHEEL
django_qiyu_utils-0.5.0.dist-info/RECORD
