Metadata-Version: 2.1
Name: django-qiyu-utils
Version: 0.5.0
Summary: Django 辅助工具类
Home-page: https://oss.qiyutech.tech/
Author: dev
Author-email: dev@qiyutech.tech
Requires-Python: >=3.9,<3.12
Classifier: Programming Language :: Python :: 3
Classifier: Programming Language :: Python :: 3.9
Classifier: Programming Language :: Python :: 3.10
Classifier: Programming Language :: Python :: 3.11
Requires-Dist: django (>=4.0,<4.3)
